README
setup.py
bin/libcnmc1048_cini_maquina.py
bin/libcnmc1048_cini_posicio.py
bin/libcnmc1048_cts.py
bin/libcnmc1048_despatx.py
bin/libcnmc1048_equips.py
bin/libcnmc1048_inventari.py
bin/libcnmc1048_lat.py
bin/libcnmc1048_lbt.py
bin/libcnmc1048_maquina.py
bin/libcnmc1048_pla_inversio.py
bin/libcnmc1048_subestacions.py
bin/libcnmc1048_subestacions_posicio.py
libcnmc1048/__init__.py
libcnmc1048/cnmc_inventari.py
libcnmc1048/cnmc_pla_inversio.py
libcnmc1048/loop.py
libcnmc1048.egg-info/PKG-INFO
libcnmc1048.egg-info/SOURCES.txt
libcnmc1048.egg-info/dependency_links.txt
libcnmc1048.egg-info/pbr.json
libcnmc1048.egg-info/requires.txt
libcnmc1048.egg-info/top_level.txt