Metadata-Version: 1.1
Name: libcnmc1048
Version: 2.2.4
Summary: Scripts per el CNMC 1048
Home-page: http://www.gisce.net
Author: GISCE Enginyeria
Author-email: devel@gisce.net
License: General Public Licence 2
Platform: UNKNOWN
Provides: libcnmc1048
